[
  {
    "uuid": "tVUX8",
    "short_url": "tVUX8",
    "original_url": "youtube.com",
    "user_id": "b2bbe303-0043-49fb-8a4e-2acb75903cd3"
  },
  {
    "uuid": "3x7A2",
    "short_url": "3x7A2",
    "original_url": "youtube.com",
    "user_id": "42f3e28e-5f58-450b-8fa6-10444553c435"
  },
  {
    "uuid": "FtkKb",
    "short_url": "FtkKb",
    "original_url": "youtube.com",
    "user_id": "6ceb882e-d4d6-42ed-b5bf-9046686f3b73"
  },
  {
    "uuid": "Uckiz",
    "short_url": "Uckiz",
    "original_url": "youtube.com",
    "user_id": "c0a53621-b9a7-4882-9670-d5ef6819e95c"
  },
  {
    "uuid": "ejmTi",
    "short_url": "ejmTi",
    "original_url": "youtube.com",
    "user_id": "c2aae817-9db5-4482-b74a-e5b005afb43b"
  },
  {
    "uuid": "FW9R0",
    "short_url": "FW9R0",
    "original_url": "youtube.com",
    "user_id": "c23c37f7-9c22-4add-8fff-5c0d43382f60"
  },
  {
    "uuid": "VJwU9",
    "short_url": "VJwU9",
    "original_url": "youtube.com",
    "user_id": "85e18859-da29-4042-bfa8-283acbc28e14"
  },
  {
    "uuid": "BDtK5",
    "short_url": "BDtK5",
    "original_url": "youtube.com",
    "user_id": "6c6d2e00-d896-4aaf-97e6-5b5ccd0d4285"
  },
  {
    "uuid": "U3mvT",
    "short_url": "U3mvT",
    "original_url": "youtube.com",
    "user_id": "55aaa379-7f3e-4f07-9334-ee8159e8b8cf"
  },
  {
    "uuid": "wNX2r",
    "short_url": "wNX2r",
    "original_url": "youtube.com",
    "user_id": "edca2c6c-34c5-4ff6-a3ea-e83fad857aea"
  },
  {
    "uuid": "By1H4",
    "short_url": "By1H4",
    "original_url": "youtube.com",
    "user_id": "4291819a-4a4b-4a71-905b-0b9aa598ff05"
  },
  {
    "uuid": "eiQX3",
    "short_url": "eiQX3",
    "original_url": "youtube.com",
    "user_id": "8a3e5d50-c386-40ef-957d-286e56e41eeb"
  },
  {
    "uuid": "JeNEV",
    "short_url": "JeNEV",
    "original_url": "youtube.com",
    "user_id": "ece5a5dc-6a01-4cab-ba25-2dc00dff72ba"
  },
  {
    "uuid": "02T7S",
    "short_url": "02T7S",
    "original_url": "youtube.com",
    "user_id": "7fbe0bc7-8156-43bf-b136-8c5aa963daa8"
  },
  {
    "uuid": "dhXLh",
    "short_url": "dhXLh",
    "original_url": "youtube.com",
    "user_id": "4fc4712c-3a63-4497-b0dd-89b082877dac"
  },
  {
    "uuid": "H6aaz",
    "short_url": "H6aaz",
    "original_url": "youtube.com",
    "user_id": "c59f5d97-407f-481a-a697-7c074a30bd05"
  },
  {
    "uuid": "QAe9r",
    "short_url": "QAe9r",
    "original_url": "youtube.com",
    "user_id": "c03dfd4b-58b6-4ea5-9e7b-3c131ed1f58c"
  },
  {
    "uuid": "aiMNp",
    "short_url": "aiMNp",
    "original_url": "youtube.com",
    "user_id": "27558f1a-50e9-4449-b11b-902a502722b1"
  },
  {
    "uuid": "cgiQZ",
    "short_url": "cgiQZ",
    "original_url": "youtube.com",
    "user_id": "e550c1ff-7a79-450b-abc9-305d35268d61"
  },
  {
    "uuid": "Al5Mc",
    "short_url": "Al5Mc",
    "original_url": "youtube.com",
    "user_id": "f71642d8-fd23-4202-a11e-5bbe8d473128"
  }
]